safucall/__init__.py
safucall/async_safucall.py
safucall/safucall.py
safucall/utils.py
safucall/multicall/__init__.py
safucall/multicall/async_multicall.py
safucall/multicall/constants.py
safucall/multicall/multicall.py
safucall-1.0.2.dist-info/LICENCE
safucall-1.0.2.dist-info/METADATA
safucall-1.0.2.dist-info/WHEEL
safucall-1.0.2.dist-info/top_level.txt
safucall-1.0.2.dist-info/RECORD
